cs_storage/__init__.py
cs_storage/screenshot.py
cs_storage/templates/index.html
cs_storage/tests/__init__.py
cs_storage/tests/test_cs_storage.py
cs_storage/tests/test_screenshot.py
cs_storage-1.11.1.dist-info/METADATA
cs_storage-1.11.1.dist-info/WHEEL
cs_storage-1.11.1.dist-info/top_level.txt
cs_storage-1.11.1.dist-info/RECORD
