Metadata-Version: 2.1
Name: cs-storage
Version: 1.11.1
Summary: A small package that is used by Compute Studio to read and write model results to google cloud storage.
Home-page: https://github.com/compute-tooling/compute-studio-storage
Author: Hank Doupe
Author-email: henrymdoupe@gmail.com
License: UNKNOWN
Platform: UNKNOWN
Classifier: Programming Language :: Python :: 3
Classifier: License :: OSI Approved :: GNU Affero General Public License v3
Classifier: Operating System :: OS Independent
Requires-Dist: marshmallow (>=3.0.0)
Requires-Dist: fsspec
Requires-Dist: gcsfs
